mcp_client_manager.py
python_code_interpreter.py
python_code_notebook.py
papermill_enhancement/__init__.py
papermill_enhancement/setup.py
papermill_enhancement/docs/conf.py
papermill_enhancement/papermill/__init__.py
papermill_enhancement/papermill/__main__.py
papermill_enhancement/papermill/abs.py
papermill_enhancement/papermill/adl.py
papermill_enhancement/papermill/cli.py
papermill_enhancement/papermill/clientwrap.py
papermill_enhancement/papermill/engines.py
papermill_enhancement/papermill/exceptions.py
papermill_enhancement/papermill/execute.py
papermill_enhancement/papermill/inspection.py
papermill_enhancement/papermill/iorw.py
papermill_enhancement/papermill/log.py
papermill_enhancement/papermill/models.py
papermill_enhancement/papermill/parameterize.py
papermill_enhancement/papermill/s3.py
papermill_enhancement/papermill/translators.py
papermill_enhancement/papermill/utils.py
papermill_enhancement/papermill/version.py
papermill_enhancement/papermill/tests/__init__.py
papermill_enhancement/papermill/tests/test_abs.py
papermill_enhancement/papermill/tests/test_adl.py
papermill_enhancement/papermill/tests/test_autosave.py
papermill_enhancement/papermill/tests/test_cli.py
papermill_enhancement/papermill/tests/test_clientwrap.py
papermill_enhancement/papermill/tests/test_conf.py
papermill_enhancement/papermill/tests/test_engines.py
papermill_enhancement/papermill/tests/test_exceptions.py
papermill_enhancement/papermill/tests/test_execute.py
papermill_enhancement/papermill/tests/test_gcs.py
papermill_enhancement/papermill/tests/test_hdfs.py
papermill_enhancement/papermill/tests/test_inspect.py
papermill_enhancement/papermill/tests/test_iorw.py
papermill_enhancement/papermill/tests/test_parameterize.py
papermill_enhancement/papermill/tests/test_s3.py
papermill_enhancement/papermill/tests/test_translators.py
papermill_enhancement/papermill/tests/test_utils.py
pycodei-0.1.9.dist-info/licenses/LICENSE
pycodei-0.1.9.dist-info/METADATA
pycodei-0.1.9.dist-info/WHEEL
pycodei-0.1.9.dist-info/entry_points.txt
pycodei-0.1.9.dist-info/top_level.txt
pycodei-0.1.9.dist-info/RECORD
