Metadata-Version: 2.4
Name: pycodei
Version: 0.1.9
Summary: An interactive Python code interpreter designed to collaborate with OpenAI and Azure AI models.
Author: Kentaro Aoki
License: MIT
Project-URL: Homepage, https://github.com/KentaroAOKI/python_code_interpreter
Requires-Python: >=3.12
License-File: LICENSE
Requires-Dist: anyio
Requires-Dist: ipykernel
Requires-Dist: jupyter
Requires-Dist: matplotlib
Requires-Dist: mcp
Requires-Dist: nbformat
Requires-Dist: numpy
Requires-Dist: openai
Requires-Dist: pandas
Requires-Dist: papermill==2.6.0
Requires-Dist: python-dotenv
Requires-Dist: requests
Requires-Dist: scikit-learn
Requires-Dist: seaborn
Requires-Dist: colorama
Requires-Dist: rich
Requires-Dist: pyfiglet
Requires-Dist: prompt_toolkit
Dynamic: license-file
